ubxserial
