Metadata-Version: 2.1
Name: ubxserial
Version: 0.0.3
Summary: Python API for sending UBX message to ublox GPS device via serial
Home-page: UNKNOWN
Author: Kai Geissdoerfer
Author-email: kai.geissdoerfer@tu-dresden.de
License: MIT
Platform: UNKNOWN
Classifier: Development Status :: 4 - Beta
Classifier: Intended Audience :: Developers
Classifier: Intended Audience :: Information Technology
Classifier: Programming Language :: Python :: 3
